pil_video/__init__.py
pil_video/pil_video.py
pil_video-0.0.4.dist-info/METADATA
pil_video-0.0.4.dist-info/WHEEL
pil_video-0.0.4.dist-info/top_level.txt
pil_video-0.0.4.dist-info/RECORD
